skeleton_nitro/__init__.py
skeleton_nitro/engine.py
skeleton_nitro-0.1.0.dist-info/METADATA
skeleton_nitro-0.1.0.dist-info/WHEEL
skeleton_nitro-0.1.0.dist-info/entry_points.txt
skeleton_nitro-0.1.0.dist-info/top_level.txt
skeleton_nitro-0.1.0.dist-info/RECORD
