Metadata-Version: 2.4
Name: skeleton-nitro
Version: 0.1.0
Summary: High-speed GPU skeletonization and augmentation engine
Requires-Dist: numpy<2.0
Requires-Dist: opencv-python
Requires-Dist: scikit-image
Requires-Dist: tqdm
